pytransformers/__init__.py
pytransformers/transformer.py
pytransformers-0.1.0.dist-info/LICENSE
pytransformers-0.1.0.dist-info/METADATA
pytransformers-0.1.0.dist-info/WHEEL
pytransformers-0.1.0.dist-info/top_level.txt
pytransformers-0.1.0.dist-info/RECORD
