Metadata-Version: 2.1
Name: pytransformers
Version: 0.1.0
Summary: create transformer models (Architecture behind chat GPT and other large language models)
Home-page: UNKNOWN
Author: omer mustafa
Author-email: <omermustafacontact@gmail.com>
License: UNKNOWN
Keywords: python,ai,Chat GPT,transformer model,transformers,bert,seq2seq,sequence to sequence,classification,chat bot,deep learning,keras
Platform: UNKNOWN
Classifier: Development Status :: 5 - Production/Stable
Classifier: Intended Audience :: Developers
Classifier: Programming Language :: Python :: 3
Classifier: Operating System :: Unix
Classifier: Operating System :: MacOS :: MacOS X
Classifier: Operating System :: Microsoft :: Windows
Requires-Python: >=3.9
License-File: LICENSE
Requires-Dist: numpy
Requires-Dist: keras
Requires-Dist: tensorflow
